setup.cfg
setup.py
Agora_Stoa.egg-info/PKG-INFO
Agora_Stoa.egg-info/SOURCES.txt
Agora_Stoa.egg-info/dependency_links.txt
Agora_Stoa.egg-info/namespace_packages.txt
Agora_Stoa.egg-info/requires.txt
Agora_Stoa.egg-info/top_level.txt
agora/__init__.py
agora/stoa/__init__.py
agora/stoa/api.py
agora/stoa/metadata.json
agora/stoa/actions/__init__.py
agora/stoa/actions/core/__init__.py
agora/stoa/actions/core/base.py
agora/stoa/actions/core/delivery.py
agora/stoa/actions/core/fragment.py
agora/stoa/actions/core/utils.py
agora/stoa/daemons/__init__.py
agora/stoa/daemons/delivery.py
agora/stoa/messaging/__init__.py
agora/stoa/messaging/reply.py
agora/stoa/server/__init__.py
agora/stoa/server/bootstrap.py
agora/stoa/server/config.py
agora/stoa/store/__init__.py
agora/stoa/store/events.py
agora/stoa/store/tables.py
agora/stoa/store/triples.py
agora/stoa/test/__init__.py
agora/stoa/test/mappings.py
agora/stoa/test/query.py
agora/stoa/test/stream.py