Metadata-Version: 1.1
Name: Agora-Stoa
Version: 0.2.0
Summary: An extensible framework to implement messaging-based services that interact with a Linked Data Platform powered by Agora
Home-page: https://github.com/smartdeveloperhub/agora-stoa.git
Author: Fernando Serena
Author-email: fernando.serena@centeropenmiddleware.com
License: Apache 2
Download-URL: https://github.com/smartdeveloperhub/agora-stoa/tarball/0.2.0
Keywords: linked-data,ontology,fragments
Platform: UNKNOWN
